setup.py
probability_distritbution/Binomialdistribution.py
probability_distritbution/Gaussiandistribution.py
probability_distritbution/Generaldistribution.py
probability_distritbution/__init__.py
probability_distritbution.egg-info/PKG-INFO
probability_distritbution.egg-info/SOURCES.txt
probability_distritbution.egg-info/dependency_links.txt
probability_distritbution.egg-info/not-zip-safe
probability_distritbution.egg-info/top_level.txt