Metadata-Version: 1.0
Name: probability-distritbution
Version: 1.0
Summary: Gaussian distributions , Binomial Distribution
Home-page: UNKNOWN
Author: UNKNOWN
Author-email: UNKNOWN
License: UNKNOWN
Platform: UNKNOWN
